django_polls/__init__.py
django_polls/admin.py
django_polls/apps.py
django_polls/forms.py
django_polls/models.py
django_polls/urls.py
django_polls/views.py
django_polls/migrations/0001_initial.py
django_polls/migrations/__init__.py
django_polls/templates/base.html
django_polls/templates/index.html
django_polls/templates/products.html
django_polls/tests/__init__.py
django_polls/tests/test_models.py
django_polls/tests/test_view.py
django_polls_pulya-0.1.3.dist-info/licenses/LICENSE
django_polls_pulya-0.1.3.dist-info/METADATA
django_polls_pulya-0.1.3.dist-info/WHEEL
django_polls_pulya-0.1.3.dist-info/top_level.txt
django_polls_pulya-0.1.3.dist-info/RECORD
