Metadata-Version: 2.4
Name: django-polls-pulya
Version: 0.1.3
Summary: A Django app to conduct web-based polls.
Author-email: Pulya <pulyaa1998@gmail.com>
License-Expression: BSD-3-Clause
Project-URL: Homepage, https://www.uzinfocom.uz/
Classifier: Environment :: Web Environment
Classifier: Framework :: Django
Classifier: Intended Audience :: Developers
Classifier: Operating System :: OS Independent
Classifier: Programming Language :: Python
Classifier: Programming Language :: Python :: 3
Classifier: Programming Language :: Python :: 3 :: Only
Classifier: Programming Language :: Python :: 3.12
Classifier: Programming Language :: Python :: 3.13
Classifier: Programming Language :: Python :: 3.14
Classifier: Topic :: Internet :: WWW/HTTP
Classifier: Topic :: Internet :: WWW/HTTP :: Dynamic Content
Requires-Python: >=3.12
License-File: LICENSE
Requires-Dist: django>=6.0
Dynamic: license-file
